README.md
setup.py
dbt/__init__.py
dbt/adapters/__init__.py
dbt/adapters/mssql/__init__.py
dbt/adapters/mssql/connections.py
dbt/adapters/mssql/impl.py
dbt/include/__init__.py
dbt/include/mssql/__init__.py
dbt/include/mssql/dbt_project.yml
dbt/include/mssql/macros/adapters.sql
dbt/include/mssql/macros/indexes.sql
dbt/include/mssql/macros/materializations/incremental/incremental.sql
dbt/include/mssql/macros/materializations/seed/seed.sql
dbt_mssql.egg-info/PKG-INFO
dbt_mssql.egg-info/SOURCES.txt
dbt_mssql.egg-info/dependency_links.txt
dbt_mssql.egg-info/requires.txt
dbt_mssql.egg-info/top_level.txt