Metadata-Version: 1.0
Name: dbt-mssql
Version: 1.0.7
Summary: The mssql adpter plugin for dbt (data build tool)
Home-page: UNKNOWN
Author: Jacob Mastel
Author-email: jacob@mastel.org
License: UNKNOWN
Platform: UNKNOWN
